pymdb
