Metadata-Version: 1.0
Name: pymdbpc
Version: 1.1
Summary: NRI Currenza RS232 MDB protocol python implimentation
Home-page: UNKNOWN
Author: Aborilov Pavel
Author-email: UNKNOWN
License: UNKNOWN
Platform: UNKNOWN
